wagtail_live/__init__.py
wagtail_live/apps.py
wagtail_live/blocks.py
wagtail_live/exceptions.py
wagtail_live/models.py
wagtail_live/signals.py
wagtail_live/urls.py
wagtail_live/utils.py
wagtail_live/version.py
wagtail_live/management/__init__.py
wagtail_live/management/commands/__init__.py
wagtail_live/management/commands/run_publisher.py
wagtail_live/migrations/__init__.py
wagtail_live/publishers/__init__.py
wagtail_live/publishers/polling.py
wagtail_live/publishers/utils.py
wagtail_live/publishers/websocket.py
wagtail_live/publishers/django_channels/__init__.py
wagtail_live/publishers/django_channels/app.py
wagtail_live/publishers/django_channels/publisher.py
wagtail_live/publishers/piesocket/__init__.py
wagtail_live/publishers/piesocket/publisher.py
wagtail_live/publishers/piesocket/utils.py
wagtail_live/publishers/redis/__init__.py
wagtail_live/publishers/redis/bus.py
wagtail_live/publishers/redis/publisher.py
wagtail_live/publishers/starlette/__init__.py
wagtail_live/publishers/starlette/app.py
wagtail_live/publishers/starlette/publisher.py
wagtail_live/publishers/websockets/__init__.py
wagtail_live/publishers/websockets/app.py
wagtail_live/publishers/websockets/publisher.py
wagtail_live/receivers/__init__.py
wagtail_live/receivers/base.py
wagtail_live/receivers/slack/__init__.py
wagtail_live/receivers/slack/receivers.py
wagtail_live/receivers/telegram/__init__.py
wagtail_live/receivers/telegram/receivers.py
wagtail_live/receivers/telegram/utils.py
wagtail_live/static/wagtail_live/js/live_posts_tracker.js
wagtail_live/static/wagtail_live/js/utils.js
wagtail_live/static/wagtail_live/js/polling/intervalpolling.js
wagtail_live/static/wagtail_live/js/polling/longpolling.js
wagtail_live/static/wagtail_live/js/websocket/django_channels.js
wagtail_live/static/wagtail_live/js/websocket/piesocket.js
wagtail_live/static/wagtail_live/js/websocket/starlette.js
wagtail_live/static/wagtail_live/js/websocket/websocket.js
wagtail_live-1.0.dist-info/LICENSE
wagtail_live-1.0.dist-info/METADATA
wagtail_live-1.0.dist-info/WHEEL
wagtail_live-1.0.dist-info/top_level.txt
wagtail_live-1.0.dist-info/RECORD
